{"api_demuxer.md":"DCLFG1oi","api_element.md":"FHwmMB3-","api_events.md":"BgatkJFi","api_player.md":"CgHEMi40","api_sources.md":"CIJ5SsX1","changelog.md":"YTvydHaY","guide_architecture.md":"D5YbEHno","guide_custom-element.md":"BNHzluhH","guide_getting-started.md":"Cxm9kI_X","guide_hdr-support.md":"DQGFcmW8","guide_local-files.md":"CnbJLSFW","guide_modules.md":"CLuIsDrH","guide_multi-track.md":"Ce0Hg5iV","guide_performance.md":"Be0VBpUB","guide_programmatic-api.md":"C-8tWXWT","guide_standards.md":"B5LJTMqO","guide_troubleshooting.md":"BVheYLLi","guide_use-cases.md":"C95NN4NQ","guide_what-is-movi-player.md":"DO9Y9KwJ","guide_why-movi-player.md":"Qz15KrWd","index.md":"BplQJjtJ","privacy-policy.md":"BbEaMQBV"}
